<?xml version="1.0"?>
<!DOCTYPE hibernate-mapping PUBLIC "-//Hibernate/Hibernate Mapping DTD 3.0//EN"
"http://hibernate.sourceforge.net/hibernate-mapping-3.0.dtd">
<!-- 
    Mapping file autogenerated by MyEclipse - Hibernate Tools
-->
<hibernate-mapping>
    <class name="com.vone.medisafe.mapping.MsPatientEscort" table="ms_patient_escort" schema="public" >
        <id name="NEscortPrimaryId" type="integer">
            <column name="n_escort_primary_id" />
            <generator class="sequence">
            	<param name="sequence">ms_patient_escort_n_escort_primary_id_seq</param>
            </generator>
        </id>
        <property name="VEscortCode" type="string">
            <column name="v_escort_code" length="15" not-null="true" />
        </property>
        <property name="VEscortType" type="string">
            <column name="v_escort_type" length="50" not-null="true" />
        </property>
        <property name="NEscortCommission" type="double">
            <column name="n_escort_commission" precision="8" scale="0" not-null="true" />
        </property>
        <property name="VWhoCreate" type="string">
            <column name="v_who_create" length="50" />
        </property>
        <property name="DWhnCreate" type="date">
            <column name="d_whn_create" length="4" />
        </property>
        <property name="VWhoChange" type="string">
            <column name="v_who_change" length="50" />
        </property>
        <property name="DWhnChange" type="date">
            <column name="d_whn_change" length="4" />
        </property>
        <set name="tbExaminations" inverse="true">
            <key>
                <column name="n_escort_id" />
            </key>
            <one-to-many class="com.vone.medisafe.mapping.TbExamination" />
        </set>
    </class>
</hibernate-mapping>
