<?xml version="1.0"?>
<!DOCTYPE hibernate-mapping PUBLIC "-//Hibernate/Hibernate Mapping DTD 3.0//EN"
"http://hibernate.sourceforge.net/hibernate-mapping-3.0.dtd">
<!-- 
    Mapping file autogenerated by MyEclipse - Hibernate Tools
-->
<hibernate-mapping>
    <class name="com.vone.medisafe.mapping.TbPatientInventory" table="tb_patient_inventory" schema="public" >
        <id name="NPiId" type="integer">
            <column name="n_pi_id" />
            <generator class="sequence">
            	<param name="sequence">tb_patient_inventory_n_pi_id_seq</param>
            </generator>
        </id>
        <many-to-one name="msPatient" class="com.vone.medisafe.mapping.MsPatient" fetch="select">
            <column name="n_pat_id" not-null="true" />
        </many-to-one>
        <many-to-one name="msItem" class="com.vone.medisafe.mapping.pojo.item.MsItem" fetch="select">
            <column name="n_item_id" not-null="true" />
        </many-to-one>
        <many-to-one name="tbItemTrx" class="com.vone.medisafe.mapping.TbItemTrx" fetch="select">
            <column name="n_item_trx_id" />
        </many-to-one>
         <many-to-one name="tbRegistration" class="com.vone.medisafe.mapping.TbRegistration" fetch="select">
            <column name="n_reg_id" />
        </many-to-one>
        <property name="VWhoCreate" type="string">
            <column name="v_who_create" length="50" />
        </property>
        <property name="VWhnCreate" type="string">
            <column name="v_whn_create" length="50" />
        </property>
        <property name="DWhoCreate" type="timestamp">
            <column name="d_who_create" length="8" />
        </property>
        <property name="DWhnCreate" type="timestamp">
            <column name="d_whn_create" length="8" />
        </property>
        <property name="NQty" type="short">
            <column name="n_qty" />
        </property>
        <property name="NQtyOut" type="short">
            <column name="n_qty_out" />
        </property>
    </class>
</hibernate-mapping>
